rispec_cli/__init__.py
rispec_cli/llms/llms-creative-orientation.txt
rispec_cli/llms/llms-rise-framework.txt
rispec_cli/llms/llms-structural-tension-charts.txt
rispec_cli/llms/llms-structural-thinking.gemini.txt
rispec_cli/llms/mcp-rise-orchestrator.md
rispec_cli/rispecs/AGENT_INSTRUCTIONS.md
rispec_cli/rispecs/ApplicationLogic.md
rispec_cli/rispecs/Configuration.md
rispec_cli/rispecs/Creative_Orientation_Operating_Guide.md
rispec_cli/rispecs/DataSchemas.md
rispec_cli/rispecs/ImplementationNotes.md
rispec_cli/rispecs/RISE_Spec.md
rispec_cli/rispecs/RISPECS.md
rispec_cli-0.2.0.dist-info/METADATA
rispec_cli-0.2.0.dist-info/WHEEL
rispec_cli-0.2.0.dist-info/entry_points.txt
rispec_cli-0.2.0.dist-info/licenses/LICENSE
rispec_cli-0.2.0.dist-info/RECORD
