Metadata-Version: 2.4
Name: rispec-cli
Version: 0.2.0
Summary: RISPEC CLI, part of RISE Spec Kit. A structural-first, spec-driven creative archaeology toolkit for LLMs and developers. Implements the RISE Framework (Reality → Inspect → Specify → Export) with multi-agent support and MCP integration.
License-File: LICENSE
Requires-Python: >=3.11
Requires-Dist: httpx[socks]
Requires-Dist: platformdirs
Requires-Dist: readchar
Requires-Dist: rich
Requires-Dist: truststore>=0.10.4
Requires-Dist: typer
